dir2tree/__init__.py
dir2tree/dir2tree.py
dir2tree-0.1.2.dist-info/LICENSE
dir2tree-0.1.2.dist-info/METADATA
dir2tree-0.1.2.dist-info/WHEEL
dir2tree-0.1.2.dist-info/top_level.txt
dir2tree-0.1.2.dist-info/RECORD
