Metadata-Version: 2.1
Name: dir2tree
Version: 0.1.2
Summary: make file directory to 2 dynamic tree-picture html,由虞元坚律师创作
Home-page: https://github.com/yyjlaw/dir2tree
Author: Yu Yuanjian
Author-email: yyjlaw@foxmail.com
License: UNKNOWN
Platform: UNKNOWN
Classifier: Programming Language :: Python :: 3
Classifier: License :: OSI Approved :: MIT License
Classifier: Operating System :: OS Independent
Requires-Dist: pyecharts (==1.8.1)
